dciauth/__init__.py
dciauth/signature.py
dciauth/version.py
dciauth/v2/__init__.py
dciauth/v2/headers.py
dciauth/v2/signature.py
dciauth/v2/time.py
dciauth-4.0.1.post202510211222.dist-info/LICENSE
dciauth-4.0.1.post202510211222.dist-info/METADATA
dciauth-4.0.1.post202510211222.dist-info/WHEEL
dciauth-4.0.1.post202510211222.dist-info/top_level.txt
dciauth-4.0.1.post202510211222.dist-info/RECORD
