Metadata-Version: 2.1
Name: dciauth
Version: 4.0.1.post202510211222
Summary: DCI authentication module used by dci-control-server and python-dciclient
Home-page: https://github.com/redhat-cip/python-dciauth
Author: Distributed CI team
Author-email: distributed-ci@redhat.com
License: Apache v2.0
Classifier: Intended Audience :: Developers
Classifier: Intended Audience :: Information Technology
Classifier: License :: OSI Approved :: Apache Software License
Classifier: Operating System :: POSIX :: Linux
Classifier: Programming Language :: Python :: 2
Classifier: Programming Language :: Python :: 3
Classifier: Topic :: Security :: Cryptography
License-File: LICENSE
